extract_ca460/__init__.py
extract_ca460/form460_page_type.py
extract_ca460/form460_summary_page.py
extract_ca460/form_460_schedule_a.py
extract_ca460/py.typed
extract_ca460-0.0.3.dist-info/WHEEL
extract_ca460-0.0.3.dist-info/METADATA
extract_ca460-0.0.3.dist-info/RECORD
