Metadata-Version: 2.3
Name: extract-ca460
Version: 0.0.3
Summary: Add your description here
Author: Alex Garcia
Author-email: Alex Garcia <alexsebastian.garcia@gmail.com>
Requires-Dist: pydantic>=2.12.5
Requires-Python: >=3.10
